hyperbolic_gradio/__init__.py
hyperbolic_gradio-0.0.5.dist-info/METADATA
hyperbolic_gradio-0.0.5.dist-info/WHEEL
hyperbolic_gradio-0.0.5.dist-info/RECORD
