Metadata-Version: 2.3
Name: hyperbolic-gradio
Version: 0.0.5
Summary: A Python package for creating Gradio applications with Hyperbolic AI models
Project-URL: homepage, https://github.com/HyperbolicLabs/hyperbolic-gradio
Project-URL: repository, https://github.com/HyperbolicLabs/hyperbolic-gradio
Author-email: AK <ahsen.khaliq@gmail.com>, YuchenJin <yuchenj@cs.washington.edu>
Classifier: License :: OSI Approved :: MIT License
Classifier: Operating System :: OS Independent
Classifier: Programming Language :: Python :: 3
Requires-Python: >=3.10
Requires-Dist: gradio>=5.5.0
Requires-Dist: openai
Provides-Extra: dev
Requires-Dist: pytest; extra == 'dev'
